selenium_wire_undetected_chromedriver_lw-1.0.1.dist-info/licenses/LICENSE
seleniumwire_gpl/__init__.py
seleniumwire_gpl/webdriver.py
selenium_wire_undetected_chromedriver_lw-1.0.1.dist-info/METADATA
selenium_wire_undetected_chromedriver_lw-1.0.1.dist-info/WHEEL
selenium_wire_undetected_chromedriver_lw-1.0.1.dist-info/top_level.txt
selenium_wire_undetected_chromedriver_lw-1.0.1.dist-info/RECORD
