Metadata-Version: 2.4
Name: selenium-wire-undetected-chromedriver-lw
Version: 1.0.1
Summary: selenium-wire-lw extension adding support for undetected_chromedriver
Author-email: LunarWatcher <oliviawolfie@pm.me>
License-Expression: GPL-3.0
Project-URL: Homepage, https://github.com/LunarWatcher/selenium-wire-undetected-chromedriver
Project-URL: Documentation, https://github.com/LunarWatcher/selenium-wire-undetected-chromedriver
Project-URL: Repository, https://github.com/LunarWatcher/selenium-wire-undetected-chromedriver.git
Project-URL: Issues, https://github.com/LunarWatcher/selenium-wire-undetected-chromedriver/issues
Project-URL: Changelog, https://github.com/LunarWatcher/selenium-wire-undetected-chromedriver/releases
Keywords: selenium,selenium-wire,selenium-wire-lw
Classifier: Development Status :: 5 - Production/Stable
Classifier: Environment :: Console
Classifier: Intended Audience :: Developers
Classifier: Topic :: System :: Archiving
Classifier: Topic :: Utilities
Classifier: Programming Language :: Python :: 3
Classifier: Programming Language :: Python :: 3.10
Classifier: Programming Language :: Python :: 3.11
Classifier: Programming Language :: Python :: 3.12
Classifier: Operating System :: POSIX :: Linux
Classifier: Operating System :: MacOS
Classifier: Operating System :: Microsoft :: Windows
Requires-Python: >=3.10
License-File: LICENSE
Requires-Dist: selenium-wire-lw>=2.0.0
Requires-Dist: undetected_chromedriver
Requires-Dist: setuptools
Dynamic: license-file
